{
  "source_lang": "py",
  "target_lang": "js",
  "template": "for _ in range(__ - 1):\n    some_secret_fn_4071()",
  "template_origin": "for _ in range(n - 1):\n    some_secret_fn_4071()",
  "templatized_node_ids": [
    7
  ],
  "translation_pairs": [
    [
      {
        "source": "for _ in range(some_variable - 1):\n    some_secret_fn_4071()",
        "target": "for (var i = 0; i < some_variable - 1; i++) {\n    some_secret_fn_4071();\n}"
      },
      {
        "source": "for _ in range(x - 1):\n    some_secret_fn_4071()",
        "target": "for (var _ = 0; _ < x - 1; _++) {\n    some_secret_fn_4071();\n}"
      }
    ],
    [
      {
        "source": "for _ in range(some_variable - 1):\n    some_secret_fn_4071()",
        "target": "for (var i = 0; i < some_variable - 1; i++) {\n    some_secret_fn_4071();\n}"
      },
      {
        "source": "for _ in range(y - 1):\n    some_secret_fn_4071()",
        "target": "for (var _ = 0; _ < y - 1; _++) {\n    some_secret_fn_4071();\n}"
      }
    ],
    [
      {
        "source": "for _ in range(some_variable - 1):\n    some_secret_fn_4071()",
        "target": "for (var i = 0; i < some_variable - 1; i++) {\n    some_secret_fn_4071();\n}"
      },
      {
        "source": "for _ in range(n - 1):\n    some_secret_fn_4071()",
        "target": "for (var _ = 0; _ < n - 1; _++) {\n    some_secret_fn_4071();\n}"
      }
    ],
    [
      {
        "source": "for _ in range(x - 1):\n    some_secret_fn_4071()",
        "target": "for (var _ = 0; _ < x - 1; _++) {\n    some_secret_fn_4071();\n}"
      },
      {
        "source": "for _ in range(y - 1):\n    some_secret_fn_4071()",
        "target": "for (var _ = 0; _ < y - 1; _++) {\n    some_secret_fn_4071();\n}"
      }
    ],
    [
      {
        "source": "for _ in range(x - 1):\n    some_secret_fn_4071()",
        "target": "for (var _ = 0; _ < x - 1; _++) {\n    some_secret_fn_4071();\n}"
      },
      {
        "source": "for _ in range(n - 1):\n    some_secret_fn_4071()",
        "target": "for (var _ = 0; _ < n - 1; _++) {\n    some_secret_fn_4071();\n}"
      }
    ],
    [
      {
        "source": "for _ in range(y - 1):\n    some_secret_fn_4071()",
        "target": "for (var _ = 0; _ < y - 1; _++) {\n    some_secret_fn_4071();\n}"
      },
      {
        "source": "for _ in range(n - 1):\n    some_secret_fn_4071()",
        "target": "for (var _ = 0; _ < n - 1; _++) {\n    some_secret_fn_4071();\n}"
      }
    ]
  ]
}
