{
  "template": "def f_gold(__: str, b: str) -> str:\n    some_secret_fn_4071()",
  "source_lang": "py",
  "target_lang": "js",
  "template_origin": "def f_gold(a: str, b: str) -> str:\n    some_secret_fn_4071()",
  "translations": {
    "def f_gold(a: str, b: str) -> str:\n    some_secret_fn_4071()": [
      "function f_gold(a, b) {\n    some_secret_fn_4071();\n}"
    ],
    "def f_gold(x: str, b: str) -> str:\n    some_secret_fn_4071()": [
      "function f_gold(x, b) {\n    some_secret_fn_4071();\n}"
    ],
    "def f_gold(word: str, b: str) -> str:\n    some_secret_fn_4071()": [
      "function f_gold(word, b) {\n    some_secret_fn_4071();\n}"
    ],
    "def f_gold(s: str, b: str) -> str:\n    some_secret_fn_4071()": [
      "function f_gold(s, b) {\n    some_secret_fn_4071();\n}"
    ],
    "def f_gold(text: str, b: str) -> str:\n    some_secret_fn_4071()": [
      "function f_gold(text, b) {\n    some_secret_fn_4071();\n}"
    ]
  }
}
