{
  "template": "__ = __",
  "lang": "py",
  "temperature": 0.7,
  "code_blocks": [
    "# Variant 1\nx = 5\n\n# Variant 2\ny = \"hello\"\n\n# Variant 3\nz = [1, 2, 3]\n\n# Variant 4\na = True\n\n# Variant 5\nb = 3.14\n\n# Variant 6\nc = None\n\n# Variant 7\nd = (1, 2, 3)\n\n# Variant 8\ne = {\"name\": \"John\", \"age\": 30}\n\n# Variant 9\nf = [True, False, True]\n\n# Variant 10\ng = 10.5",
    "x = 5",
    "y = \"hello\"",
    "z = [1, 2, 3]",
    "a = True",
    "b = 3.14",
    "c = (1, 2, 3)",
    "d = {\"name\": \"John\", \"age\": 25}",
    "e = None",
    "f = [True, False, True]",
    "g = 10",
    "x = 5",
    "y = \"hello\"",
    "z = [1, 2, 3]",
    "a = True",
    "b = 3.14",
    "c = None",
    "d = (1, 2, 3)",
    "e = {\"key\": \"value\"}",
    "f = [True, False, True]",
    "g = 10",
    "a = 10",
    "x = \"hello\"",
    "num = 3.14",
    "count = 0",
    "result = True",
    "name = \"John\"",
    "value = [1, 2, 3]",
    "total = 1000.0",
    "flag = False",
    "text = \"Lorem ipsum\"",
    "x = 5",
    "y = \"hello\"",
    "z = 3.14",
    "a = True",
    "b = [1, 2, 3]",
    "c = (1, 2, 3)",
    "d = {\"name\": \"John\", \"age\": 30}",
    "e = None",
    "f = [True, False, True]",
    "g = (1.1, 2.2, 3.3)",
    "x = 5",
    "y = \"hello\"",
    "z = [1, 2, 3]",
    "a = True",
    "b = 3.14",
    "c = (1, 2, 3)",
    "d = {\"name\": \"John\", \"age\": 25}",
    "e = None",
    "f = [True, False, True]",
    "g = 10.5",
    "x = 5",
    "y = \"Hello\"",
    "z = True",
    "a = 3.14",
    "b = [1, 2, 3]",
    "c = {\"name\": \"John\", \"age\": 25}",
    "d = (1, 2, 3)",
    "e = None",
    "f = 10 + 5j",
    "g = [True, False, True]",
    "a = 5",
    "x = \"hello\"",
    "num = 3.14",
    "name = \"John Doe\"",
    "is_valid = True",
    "count = 10",
    "result = calculate()",
    "value = None",
    "lst = [1, 2, 3]",
    "total = 1000.0",
    "x = 5",
    "y = \"hello\"",
    "z = True",
    "a = 3.14",
    "b = [1, 2, 3]",
    "c = {\"name\": \"John\", \"age\": 25}",
    "d = (1, 2, 3)",
    "e = None",
    "f = 10 + 5",
    "g = \"world\" + \"!\"",
    "x = 5",
    "y = \"hello\"",
    "z = [1, 2, 3]",
    "a = True",
    "b = 3.14",
    "c = {'name': 'John', 'age': 30}",
    "d = (1, 2, 3)",
    "e = None",
    "f = [True, False, True]",
    "g = 10 + 5j",
    "x = 5",
    "y = \"hello\"",
    "z = True",
    "a = 3.14",
    "b = [1, 2, 3]",
    "c = {\"name\": \"John\", \"age\": 30}",
    "d = (1, 2, 3)",
    "e = None",
    "f = 10 + 20",
    "g = [x for x in range(5)]",
    "a = 5",
    "x = \"hello\"",
    "count = 0",
    "result = True",
    "pi = 3.14159",
    "name = \"John\"",
    "age = 25",
    "is_valid = False",
    "score = 98.5",
    "size = \"small\"",
    "a = 10",
    "b = \"hello\"",
    "c = 3.14",
    "d = True",
    "e = [1, 2, 3]",
    "f = {\"key\": \"value\"}",
    "g = (1, 2, 3)",
    "h = None",
    "i = lambda x: x**2",
    "j = range(5)",
    "# Variant 1\nx = 5\n\n# Variant 2\ny = \"Hello\"\n\n# Variant 3\nz = 3.14\n\n# Variant 4\na = True\n\n# Variant 5\nb = [1, 2, 3]\n\n# Variant 6\nc = {\"name\": \"John\", \"age\": 30}\n\n# Variant 7\nd = (1, 2, 3)\n\n# Variant 8\ne = None\n\n# Variant 9\nf = 10 + 5\n\n# Variant 10\ng = len(\"Hello World\")",
    "a = 10",
    "x = \"hello\"",
    "num = 3.14",
    "name = \"John\"",
    "count = 1000",
    "result = True",
    "value = [1, 2, 3]",
    "pi = 3.14159",
    "flag = False",
    "data = {\"name\": \"Alice\", \"age\": 25}",
    "x = 5",
    "y = \"Hello\"",
    "z = [1, 2, 3]",
    "a = 3.14",
    "b = True",
    "c = None",
    "d = (1, 2, 3)",
    "e = {'name': 'John', 'age': 25}",
    "f = [True, False, True]",
    "g = \"Python\"",
    "x = 5",
    "y = \"Hello\"",
    "z = 3.14",
    "a = True",
    "b = [1, 2, 3]",
    "c = {\"name\": \"John\", \"age\": 30}",
    "d = (1, 2, 3)",
    "e = None",
    "f = lambda x: x * 2",
    "g = [i for i in range(5)]",
    "a = 5",
    "x = \"hello\"",
    "count = 0",
    "pi = 3.14",
    "is_valid = True",
    "name = \"John Doe\"",
    "number_of_students = 25",
    "result = 42.0",
    "is_even = False",
    "message = \"Hello, world!\"",
    "x = 10",
    "y = \"hello\"",
    "z = [1, 2, 3]",
    "a = True",
    "b = 3.14",
    "c = (1, 2, 3)",
    "d = {\"name\": \"John\", \"age\": 25}",
    "e = None",
    "f = [True, False, True]",
    "g = 42",
    "x = 5",
    "y = \"Hello\"",
    "z = [1, 2, 3]",
    "a = True",
    "b = 3.14",
    "c = (1, 2, 3)",
    "d = None",
    "e = {\"name\": \"John\", \"age\": 25}",
    "f = [True, False, True]",
    "g = 10 + 5j",
    "x = 5",
    "y = \"hello\"",
    "z = [1, 2, 3]",
    "a = True",
    "b = 3.14159",
    "c = (1, 2, 3)",
    "d = {\"key\": \"value\"}",
    "e = None",
    "f = [True, False]",
    "g = 42",
    "x = 5",
    "y = \"hello\"",
    "z = [1, 2, 3]",
    "a = True",
    "b = 3.14",
    "c = None",
    "d = (1, 2, 3)",
    "e = {\"name\": \"John\", \"age\": 30}",
    "f = [True, False, True]",
    "g = \"world\"",
    "a = 5",
    "x = \"Hello\"",
    "count = 0",
    "value = 3.14",
    "is_true = True",
    "name = \"John\"",
    "result = 42",
    "nums = [1, 2, 3]",
    "message = \"Hello, world!\"",
    "score = 100",
    "x = 10",
    "y = \"hello\"",
    "z = True",
    "a = 3.14",
    "b = [1, 2, 3]",
    "c = {\"name\": \"John\", \"age\": 25}",
    "d = (1, 2, 3)",
    "e = None",
    "f = 100",
    "g = False",
    "x = 5",
    "y = \"Hello\"",
    "z = [1, 2, 3]",
    "a = True",
    "b = 3.14",
    "c = (1, 2, 3)",
    "d = {\"name\": \"John\", \"age\": 30}",
    "e = None",
    "f = [True, False, True]",
    "g = 10 + 2j",
    "x = 10",
    "y = \"hello\"",
    "z = True",
    "a = 3.14",
    "b = [1, 2, 3]",
    "c = (4, 5, 6)",
    "d = {\"name\": \"John\", \"age\": 30}",
    "e = None",
    "f = lambda x: x**2",
    "g = [i for i in range(5)]",
    "x = 42",
    "y = \"hello\"",
    "z = True",
    "a = 3.14",
    "b = [1, 2, 3]",
    "c = {'name': 'John', 'age': 25}",
    "d = (1, 2, 3)",
    "e = None",
    "f = lambda x: x**2",
    "g = 10 + 20",
    "x = 10",
    "name = \"John\"",
    "y = 3.14",
    "is_valid = True",
    "age = 25",
    "result = None",
    "color = \"blue\"",
    "count = 1000",
    "is_active = False",
    "pi = 3.14159",
    "x = 5",
    "y = \"hello\"",
    "z = [1, 2, 3]",
    "a = True",
    "b = 3.14",
    "c = (1, 2, 3)",
    "d = {'name': 'John', 'age': 25}",
    "e = None",
    "f = [True, False, True]",
    "g = 10.5",
    "x = 5",
    "y = \"hello\"",
    "z = [1, 2, 3]",
    "a = 3.14",
    "b = True",
    "c = None",
    "d = {'name': 'John', 'age': 25}",
    "e = (1, 2, 3)",
    "f = lambda x: x + 1",
    "g = [True, False, True]"
  ],
  "num_code_blocks": 282
}
